midone/__init__.py
midone/gameconfig.py
midone/accounting/__init__.py
midone/accounting/pnl.py
midone/accounting/pnlutil.py
midone/accounting/stdsignalpnl.py
midone/attackers/__init__.py
midone/attackers/attacker.py
midone/attackers/attackerwithhistorymixin.py
midone/attackers/attackerwithpnl.py
midone/attackers/baseattacker.py
midone/attackers/calibratedattacker.py
midone/datasources/__init__.py
midone/datasources/streamgenerator.py
midone/datasources/streamgeneratorgenerator.py
midone/datasources/streamurl.py
midone/examples/__init__.py
midone/examples/calibratedmacdattacker.py
midone/examples/empiricalmeanreversionattacker.py
midone/examples/macdattacker.py
midone/examples/meanreversionattacker.py
midone/examples/randomattackerwithpnl.py
midone/mixins/__init__.py
midone/mixins/historymixin.py
midone/riverstats/__init__.py
midone/riverstats/fewmean.py
midone/riverstats/fewvar.py
midone/rivertransformers/__init__.py
midone/rivertransformers/macd.py
midone/runners/__init__.py
midone/runners/forgetfulrunner.py
midone/syntheticdata/__init__.py
midone/syntheticdata/momentumregimes.py
midone-1.0.4.dist-info/LICENSE
midone-1.0.4.dist-info/METADATA
midone-1.0.4.dist-info/WHEEL
midone-1.0.4.dist-info/entry_points.txt
midone-1.0.4.dist-info/top_level.txt
midone-1.0.4.dist-info/RECORD
