Metadata-Version: 2.1
Name: midone
Version: 1.0.4
Summary: Online autonomous time series prediction of near martingales
Home-page: https://github.com/microprediction/midone
Author: microprediction
Author-email: peter.cotton@microprediction.com
License: MIT
Classifier: License :: OSI Approved :: MIT License
Classifier: Programming Language :: Python :: 3
Classifier: Programming Language :: Python :: 3.10
Classifier: Programming Language :: Python :: 3.12
License-File: LICENSE
Requires-Dist: numpy
Requires-Dist: river
Requires-Dist: requests
Requires-Dist: statsmodels
Provides-Extra: tests
Requires-Dist: pandas-ta; extra == "tests"
Requires-Dist: flake8; extra == "tests"
Requires-Dist: pytest; extra == "tests"
